{
  "articles": [
    {
      "article_id": 99,
      "filename": "dadassist-article-099.html",
      "source_url": "https://www.handbook.vla.vic.gov.au/guideline-8-family-violence-intervention-order-cases",
      "title": "Guideline 8 \u2013 family violence intervention order cases",
      "generated_date": "2025-11-16T10:35:00+11:00",
      "live_url": "https://dadassist.com.au/posts/articles/dadassist-article-099.html",
      "category": "Family Violence"
    },
    {
      "article_id": 100,
      "filename": "dadassist-article-100.html",
      "title": "\ufeffLegal Aid ACT",
      "source_url": "https://www.legaladvice.com.au/legal-advice/legal-aid-act-247",
      "generated_date": "2025-11-16T11:10:45.729472",
      "live_url": "https://dadassist.com.au/posts/articles/dadassist-article-100.html",
      "category": "Parenting & Custody"
    },
    {
      "article_id": 101,
      "filename": "dadassist-article-101.html",
      "title": "Family court",
      "source_url": "https://cspm.csyw.qld.gov.au/procedures/engage-with-other-jurisdictions/family-courts",
      "generated_date": "2025-11-17T09:35:34.766731",
      "live_url": "https://dadassist.com.au/posts/articles/dadassist-article-101.html",
      "category": "Family Violence"
    },
    {
      "article_id": 102,
      "filename": "dadassist-article-102.html",
      "title": "Prenuptial Agreements in Victoria",
      "source_url": "https://www.aitken.com.au/news/prenuptial-agreements-in-victoria",
      "generated_date": "2025-11-24T09:35:09.218672",
      "live_url": "https://dadassist.com.au/posts/articles/dadassist-article-102.html",
      "category": "Legal Procedures"
    },
    {
      "article_id": 103,
      "filename": "dadassist-article-103.html",
      "title": "De Facto Separation",
      "source_url": "https://www.armstronglegal.com.au/family-law/de-facto-relationship/de-facto-separation/",
      "generated_date": "2025-12-01T09:37:58.580409",
      "live_url": "https://dadassist.com.au/posts/articles/dadassist-article-103.html",
      "category": "Parenting & Custody"
    },
    {
      "article_id": 104,
      "filename": "dadassist-article-104.html",
      "title": "How Do You Get Parental Rights in Australia? Everything You Need to Know",
      "source_url": "https://familylawyersmackay.com.au/how-do-you-get-parental-rights/",
      "generated_date": "2025-12-08T09:39:14.110407",
      "live_url": "https://dadassist.com.au/posts/articles/dadassist-article-104.html",
      "category": "Child Support"
    },
    {
      "article_id": 105,
      "filename": "dadassist-article-105.html",
      "title": "How Are Assets Divided In A Divorce Australia: Affinitas",
      "source_url": "https://www.affinitaslegal.com.au/how-are-assets-divided-in-a-divorce-australia/",
      "generated_date": "2025-12-14T06:04:20.745520",
      "live_url": "https://dadassist.com.au/posts/articles/dadassist-article-105.html",
      "category": "Mental Health"
    }
  ],
  "next_article_id": 106,
  "last_updated": "2025-12-14T06:04:20.745526",
  "description": "Tracks all generated DadAssist articles with source URLs and metadata. Starting from ID 99 to account for 98 existing articles with old naming scheme."
}